VolcanoSort/__init__.py
VolcanoSort/volcano.py
VolcanoSort-1.0.4.dist-info/LICENSE
VolcanoSort-1.0.4.dist-info/METADATA
VolcanoSort-1.0.4.dist-info/WHEEL
VolcanoSort-1.0.4.dist-info/top_level.txt
VolcanoSort-1.0.4.dist-info/RECORD
