Metadata-Version: 2.1
Name: VolcanoSort
Version: 1.0.4
Summary: The hottest sorting algorithm around!
Home-page: https://github.com/jhracho/VolcanoSort
Author: Jake Hracho
Author-email: volcanosort@gmail.com
License: UNKNOWN
Project-URL: Bug Tracker, https://github.com/jhracho/VolcanoSort/issues
Platform: UNKNOWN
Classifier: Programming Language :: Python :: 3
Classifier: License :: OSI Approved :: MIT License
Classifier: Operating System :: OS Independent
Requires-Python: >=3.6
License-File: LICENSE
